cased_django/__init__.py
cased_django/cased_model_event.py
cased_django/client.py
cased_django/conf.py
cased_django/event_manager.py
cased_django/middleware.py
cased_django-0.6.0.dist-info/LICENSE
cased_django-0.6.0.dist-info/METADATA
cased_django-0.6.0.dist-info/WHEEL
cased_django-0.6.0.dist-info/top_level.txt
cased_django-0.6.0.dist-info/RECORD
